Metadata-Version: 2.1
Name: sloris
Version: 1.0.3
Summary: Slow Loris denial of service attack
Home-page: https://gitlab.com/richardnagy/security/sloris
Author: Richard Antal Nagy
Author-email: nagy.richard.antal@gmail.com
License: MIT
Keywords: sloris,dos,security,hacking,denial of service
Platform: UNKNOWN
Classifier: Intended Audience :: Developers
Classifier: Intended Audience :: Information Technology
Classifier: Topic :: Security
Classifier: License :: OSI Approved :: MIT License
Classifier: Programming Language :: Python :: 3
Classifier: Operating System :: OS Independent
Requires-Python: >=3.8
License-File: LICENSE
